{"id":"109c0c8b-8a84-4b59-a7f6-b21cf313b32a","revision":0,"last_node_id":8,"last_link_id":8,"nodes":[{"id":8,"type":"Save Text File","pos":[3490,440],"size":[315,226],"flags":{},"order":1,"mode":0,"inputs":[{"localized_name":"text","name":"text","type":"STRING","link":6},{"localized_name":"path","name":"path","type":"STRING","widget":{"name":"path"},"link":8},{"localized_name":"filename_prefix","name":"filename_prefix","type":"STRING","widget":{"name":"filename_prefix"},"link":null},{"localized_name":"filename_delimiter","name":"filename_delimiter","type":"STRING","widget":{"name":"filename_delimiter"},"link":null},{"localized_name":"filename_number_padding","name":"filename_number_padding","type":"INT","widget":{"name":"filename_number_padding"},"link":null},{"localized_name":"file_extension","name":"file_extension","shape":7,"type":"STRING","widget":{"name":"file_extension"},"link":null},{"localized_name":"encoding","name":"encoding","shape":7,"type":"STRING","widget":{"name":"encoding"},"link":null},{"localized_name":"filename_suffix","name":"filename_suffix","shape":7,"type":"STRING","widget":{"name":"filename_suffix"},"link":null}],"outputs":[],"properties":{"cnr_id":"was-node-suite-comfyui","ver":"1.0.2","Node name for S&R":"Save Text File"},"widgets_values":["./ComfyUI/output/[time(%Y-%m-%d)]","ComfyUI","_",4,".txt","utf-8",""]},{"id":7,"type":"DatasetGenerator","pos":[2960,460],"size":[400,200],"flags":{},"order":0,"mode":0,"inputs":[{"localized_name":"character","name":"character","type":"COMBO","widget":{"name":"character"},"link":null},{"localized_name":"game_name","name":"game_name","type":"STRING","widget":{"name":"game_name"},"link":null},{"localized_name":"additional_caption","name":"additional_caption","shape":7,"type":"STRING","widget":{"name":"additional_caption"},"link":null}],"outputs":[{"localized_name":"dataset_path","name":"dataset_path","type":"STRING","links":[6,8]}],"properties":{"cnr_id":"vnccs","ver":"05cf428c768d16ab84dfcd93364315143c11ac6c","Node name for S&R":"DatasetGenerator"},"widgets_values":["NewCharacter1","VN"," "]}],"links":[[6,7,0,8,0,"STRING"],[8,7,0,8,1,"STRING"]],"groups":[],"config":{},"extra":{"ds":{"scale":1.116781577942508,"offset":[-1879.0261613335524,-178.71331705026483]}},"version":0.4}